philologic/Config.py
philologic/TagCensus.py
philologic/__init__.py
philologic/shlax.py
philologic/shlaxtree.py
philologic/loadtime/LoadFilters.py
philologic/loadtime/LoadOptions.py
philologic/loadtime/Loader.py
philologic/loadtime/OHCOVector.py
philologic/loadtime/Parser.py
philologic/loadtime/PlainTextParser.py
philologic/loadtime/PostFilters.py
philologic/loadtime/__init__.py
philologic/loadtime/__main__.py
philologic/runtime/DB.py
philologic/runtime/FragmentParser.py
philologic/runtime/HitList.py
philologic/runtime/HitWrapper.py
philologic/runtime/MetadataQuery.py
philologic/runtime/ObjectFormatter.py
philologic/runtime/Query.py
philologic/runtime/QuerySyntax.py
philologic/runtime/WSGIHandler.py
philologic/runtime/__init__.py
philologic/runtime/access_control.py
philologic/runtime/citations.py
philologic/runtime/find_similar_words.py
philologic/runtime/get_text.py
philologic/runtime/link.py
philologic/runtime/pages.py
philologic/runtime/web_config.py
philologic/runtime/reports/__init__.py
philologic/runtime/reports/aggregation.py
philologic/runtime/reports/bibliography.py
philologic/runtime/reports/collocation.py
philologic/runtime/reports/concordance.py
philologic/runtime/reports/frequency.py
philologic/runtime/reports/generate_word_frequency.py
philologic/runtime/reports/kwic.py
philologic/runtime/reports/landing_page.py
philologic/runtime/reports/navigation.py
philologic/runtime/reports/table_of_contents.py
philologic/runtime/reports/time_series.py
philologic/utils/__init__.py
philologic/utils/convert_entities.py
philologic/utils/line_count.py
philologic/utils/load_module.py
philologic/utils/metadata_type_handler.py
philologic/utils/pretty_print.py
philologic/utils/sort.py
philologic-5.1.0.1.dist-info/licenses/LICENSE
philologic-5.1.0.1.dist-info/METADATA
philologic-5.1.0.1.dist-info/WHEEL
philologic-5.1.0.1.dist-info/top_level.txt
philologic-5.1.0.1.dist-info/RECORD
